lintsampler/__init__.py
lintsampler/lintsampler.py
lintsampler/sampling.py
lintsampler/utils.py
lintsampler/density_structures/__init__.py
lintsampler/density_structures/base.py
lintsampler/density_structures/grid.py
lintsampler/density_structures/tree.py
lintsampler-1.0.0.dist-info/LICENSE
lintsampler-1.0.0.dist-info/METADATA
lintsampler-1.0.0.dist-info/WHEEL
lintsampler-1.0.0.dist-info/top_level.txt
lintsampler-1.0.0.dist-info/RECORD
