Metadata-Version: 2.1
Name: lintsampler
Version: 1.0.0
Summary: Efficient random sampling via linear interpolation.
Author-email: "Aneesh P. Naik" <aneesh.naik@roe.ac.uk>, "Michael S. Petersen" <michael.petersen@roe.ac.uk>
Project-URL: Homepage, https://github.com/aneeshnaik/lintsampler
Project-URL: Documentation, https://lintsampler.readthedocs.io
Keywords: python,statistics,numpy,sampling,random
Classifier: Programming Language :: Python :: 3
Classifier: License :: OSI Approved :: MIT License
Classifier: Operating System :: OS Independent
Classifier: Intended Audience :: Science/Research
Classifier: Topic :: Scientific/Engineering
Requires-Python: >=3.8
License-File: LICENSE
Requires-Dist: numpy <2.0,>=1.17
Requires-Dist: scipy <2.0,>=1.9
